tunsberg/__init__.py
tunsberg/konfig.py
tunsberg/responses.py
tunsberg/utsikten.py
tunsberg-0.2.1.dist-info/licenses/LICENSE.md
tunsberg-0.2.1.dist-info/METADATA
tunsberg-0.2.1.dist-info/WHEEL
tunsberg-0.2.1.dist-info/top_level.txt
tunsberg-0.2.1.dist-info/RECORD
