Metadata-Version: 2.4
Name: tunsberg
Version: 0.2.1
Summary: A collection of opinionated methods, functions, classes and utils for Python, FastAPI and related libraries.
Home-page: https://github.com/kilobyteno/tunsberg
Author: Kilobyte AS
License: MIT
Project-URL: Github, https://github.com/kilobyteno/tunsberg
Classifier: Programming Language :: Python
Classifier: Programming Language :: Python :: 3
Classifier: Programming Language :: Python :: 3.9
Classifier: Programming Language :: Python :: 3.10
Classifier: Programming Language :: Python :: 3.11
Classifier: Programming Language :: Python :: 3.12
Requires-Python: >=3.9
License-File: LICENSE.md
Requires-Dist: fastapi>=0.110.1
Requires-Dist: starlette>=0.37.2
Requires-Dist: pydantic>=2.7.0
Requires-Dist: fastapi-pagination>=0.12.0
Dynamic: author
Dynamic: classifier
Dynamic: description
Dynamic: description-content-type
Dynamic: home-page
Dynamic: license
Dynamic: license-file
Dynamic: project-url
Dynamic: requires-dist
Dynamic: requires-python
Dynamic: summary
